{
  "app": [
    {
      "player": {
        "x": -4.5,
        "y": 1.100000023841858,
        "z": -4.5
      }
    }
  ],
  "model": [],
  "solidground": [
    {
      "p": {
        "x": 0,
        "y": 0,
        "z": 0
      },
      "r": {
        "x": 0,
        "y": 0,
        "z": 0
      },
      "s": {
        "x": 20,
        "y": 1,
        "z": 20
      },
      "col": "#FFFFFF",
      "met": 0,
      "ref": 0,
      "glo": 0.3
    }
  ],
  "solidbox": [],
  "ground": [],
  "box": [],
  "image": [],
  "html": [
    {
      "p": {
        "x": -8,
        "y": 2,
        "z": -10
      },
      "r": {
        "x": 89.99999999999999,
        "y": 0,
        "z": 0
      },
      "s": {
        "x": 4,
        "y": 1,
        "z": 4
      },
      "market": "me",
      "asset": "https://ordinals.com/content/3e2c438da1b45254ed872212113df77ba5730a0af699654f6933a109be89daebi0"
    }
  ],
  "video": [],
  "youtube": [
    {
      "p": {
        "x": 0,
        "y": 5,
        "z": -10
      },
      "r": {
        "x": 89.99999999999999,
        "y": 0,
        "z": 0
      },
      "s": {
        "x": 10,
        "y": 1,
        "z": 10
      },
      "asset": "https://youtu.be/3hCjJ1XQZaU"
    }
  ],
  "audio": [],
  "water": [],
  "text": [],
  "collider": [
    {
      "p": {
        "x": 0,
        "y": 0.5,
        "z": 0
      },
      "r": {
        "x": 0,
        "y": 0,
        "z": 0
      },
      "s": {
        "x": 1,
        "y": 1,
        "z": 1
      }
    }
  ]
}